barycentric_interpolation_np
